agentlink/agent/__init__.py
agentlink/agent/agent.py
agentlink/bus/blackboard.py
agentlink/bus/config.py
agentlink/bus/core.py
agentlink/bus/message.py
agentlink/bus/queue.py
agentlink-0.1.1.dist-info/LICENSE
agentlink-0.1.1.dist-info/METADATA
agentlink-0.1.1.dist-info/WHEEL
agentlink-0.1.1.dist-info/RECORD
