Metadata-Version: 2.1
Name: agentlink
Version: 0.1.1
Summary: 
Home-page: https://github.com/2mmanu/agentLINK
License: Apache-2.0
Author: 2mmanu
Author-email: emmanuele.lacavalla@gmail.com
Requires-Python: >=3.11,<4.0
Classifier: License :: OSI Approved :: Apache Software License
Classifier: Programming Language :: Python :: 3
Classifier: Programming Language :: Python :: 3.11
Classifier: Programming Language :: Python :: 3.12
Requires-Dist: confluent-kafka (==2.2.0)
Requires-Dist: pydantic-settings (==2.3.4)
Requires-Dist: redis (==5.0.7)
Project-URL: Repository, https://github.com/2mmanu/agentLINK
